bench_af_components/detectors/__init__.py
bench_af_components/detectors/poser_1_belief_state_induction/__init__.py
bench_af_components/detectors/poser_1_belief_state_induction/main.py
bench_af_components/detectors/poser_2_activation_noising/__init__.py
bench_af_components/detectors/poser_2_activation_noising/main.py
bench_af_components/detectors/poser_3_bad_finetuning_rate/__init__.py
bench_af_components/detectors/poser_3_bad_finetuning_rate/main.py
bench_af_components/detectors/poser_4_suspicious_concept_identification/__init__.py
bench_af_components/detectors/poser_4_suspicious_concept_identification/main.py
bench_af_components/detectors/poser_5_decision_making_speed/__init__.py
bench_af_components/detectors/poser_5_decision_making_speed/main.py
bench_af_components/detectors/poser_6_attentiveness_to_oversight/__init__.py
bench_af_components/detectors/poser_6_attentiveness_to_oversight/main.py
bench_af_components/detectors/stupid/__init__.py
bench_af_components/detectors/stupid/main.py
bench_af_components/detectors/stupid/run.py
bench_af_components/detectors/test/__init__.py
bench_af_components/detectors/test/main.py
bench_af_components/detectors/test_nnsight/__init__.py
bench_af_components/detectors/test_nnsight/main.py
bench_af_components/detectors/test_tl/__init__.py
bench_af_components/detectors/test_tl/dev.py
bench_af_components/detectors/test_tl/main.py
bench_af_components/detectors/zero_out_weights/__init__.py
bench_af_components/detectors/zero_out_weights/run.py
bench_af_components/environments/__init__.py
bench_af_components/environments/blackmail/__init__.py
bench_af_components/environments/blackmail/main.py
bench_af_components/environments/blackmail/process_emails.py
bench_af_components/environments/blackmail/scorer.py
bench_af_components/environments/blackmail_no_tools/__init__.py
bench_af_components/environments/blackmail_no_tools/main.py
bench_af_components/environments/blackmail_no_tools/process_txt.py
bench_af_components-0.1.0.dist-info/licenses/LICENSE
bench_af_components-0.1.0.dist-info/METADATA
bench_af_components-0.1.0.dist-info/WHEEL
bench_af_components-0.1.0.dist-info/top_level.txt
bench_af_components-0.1.0.dist-info/RECORD
