Metadata-Version: 2.4
Name: bench-af-components
Version: 0.1.0
Summary: Add your description here
Requires-Python: >=3.12
License-File: LICENSE
Requires-Dist: bench-af>=0.1.3
Requires-Dist: mypy>=1.17.1
Dynamic: license-file
